kivy_garden/collider/_version.py
kivy_garden/collider/_collider.cpython-311-darwin.so
kivy_garden/collider/__init__.py
kivy_garden/collider/tests/test_import.py
kivy_garden.collider-0.1.3.dist-info/RECORD
kivy_garden.collider-0.1.3.dist-info/LICENSE
kivy_garden.collider-0.1.3.dist-info/WHEEL
kivy_garden.collider-0.1.3.dist-info/top_level.txt
kivy_garden.collider-0.1.3.dist-info/AUTHORS.txt
kivy_garden.collider-0.1.3.dist-info/METADATA
