Metadata-Version: 2.1
Name: kivy_garden.collider
Version: 0.1.3
Summary: Collides a point with a space defined by a curve.
Home-page: https://github.com/kivy-garden/collider
Author: Kivy
Author-email: kivy@kivy.org
Project-URL: Bug Reports, https://github.com/kivy-garden/collider/issues
Project-URL: Source, https://github.com/kivy-garden/collider
Keywords: Kivy kivy-garden
Classifier: Development Status :: 4 - Beta
Classifier: Intended Audience :: Developers
Classifier: Topic :: Software Development :: Libraries
Classifier: License :: OSI Approved :: MIT License
Classifier: Programming Language :: Python :: 3.8
Classifier: Programming Language :: Python :: 3.9
Classifier: Programming Language :: Python :: 3.10
Classifier: Programming Language :: Python :: 3.11
Classifier: Programming Language :: Python :: 3.12
License-File: LICENSE
License-File: AUTHORS.txt
Requires-Dist: kivy
Provides-Extra: dev
Requires-Dist: pytest>=3.6; extra == "dev"
Requires-Dist: wheel; extra == "dev"
Requires-Dist: pytest-cov; extra == "dev"
Requires-Dist: pytest-asyncio; extra == "dev"
Requires-Dist: sphinx_rtd_theme; extra == "dev"
Provides-Extra: ci
Requires-Dist: coveralls; extra == "ci"
Requires-Dist: pycodestyle; extra == "ci"
